GenomiX.py
pyproject.toml
GenomiX.egg-info/PKG-INFO
GenomiX.egg-info/SOURCES.txt
GenomiX.egg-info/dependency_links.txt
GenomiX.egg-info/requires.txt
GenomiX.egg-info/top_level.txt