Metadata-Version: 2.1
Name: GenomiX
Version: 1.0.2
Summary: Use it to import very handy functions.
Author-email: "Florian CHARRIAT (CIRAD)" <florian.charriat@cirad.fr>
Requires-Python: >=3.8
Requires-Dist: biopython
Requires-Dist: argparse
Requires-Dist: pandas
